great_expectations_provider_cta/__init__.py
great_expectations_provider_cta/example_dags/__init__.py
great_expectations_provider_cta/example_dags/example_great_expectations_dag.py
great_expectations_provider_cta/operators/__init__.py
great_expectations_provider_cta/operators/great_expectations_cta.py
include/great_expectations_cta/object_configs/__init__.py
include/great_expectations_cta/object_configs/example_checkpoint_config.py
include/great_expectations_cta/object_configs/example_data_context_config.py
include/great_expectations_cta/object_configs/example_runtime_batch_request_for_plugin_expectation.py
include/great_expectations_cta/plugins/__init__.py
include/great_expectations_cta/plugins/expectations/__init__.py
include/great_expectations_cta/plugins/expectations/expect_column_values_to_be_alphabetical.py
tests/__init__.py
tests/operators/__init__.py
tests/operators/test_great_expectations_cta.py
airflow_provider_great_expectations_cta-0.2.4.dist-info/LICENSE.txt
airflow_provider_great_expectations_cta-0.2.4.dist-info/METADATA
airflow_provider_great_expectations_cta-0.2.4.dist-info/WHEEL
airflow_provider_great_expectations_cta-0.2.4.dist-info/entry_points.txt
airflow_provider_great_expectations_cta-0.2.4.dist-info/top_level.txt
airflow_provider_great_expectations_cta-0.2.4.dist-info/RECORD
